{
 "charts": [],
 "content": "[{\"id\":\"team-header\",\"type\":\"header\",\"data\":{\"text\":\"<span class=\\\"h4\\\">Team</span>\",\"col\":12}},{\"id\":\"team-summary\",\"type\":\"paragraph\",\"data\":{\"text\":\"Manage the operator team and shared ownership of the control plane from one team workspace.\",\"col\":12}},{\"id\":\"team-team\",\"type\":\"shortcut\",\"data\":{\"shortcut_name\":\"Team\",\"col\":4}}]",
 "creation": "2026-04-14 00:00:00.000000",
 "custom_blocks": [],
 "docstatus": 0,
 "doctype": "Workspace",
 "for_user": "",
 "hide_custom": 0,
 "icon": "octicon octicon-people",
 "idx": 0,
 "indicator_color": "green",
 "is_hidden": 0,
 "label": "Team",
 "links": [],
 "modified": "2026-04-14 00:00:00.000000",
 "modified_by": "Administrator",
 "module": "Press",
 "name": "Team",
 "number_cards": [],
 "owner": "Administrator",
 "parent_page": "",
 "public": 1,
 "quick_lists": [],
 "roles": [],
 "sequence_id": 37.0,
 "shortcuts": [
  {
   "color": "Green",
   "doc_view": "List",
   "label": "Tenants",
   "link_to": "Team",
   "stats_filter": "[[\"Team\",\"enabled\",\"=\",1,false]]",
   "type": "DocType"
  },
  {
   "color": "Blue",
   "doc_view": "List",
   "label": "Team",
   "link_to": "Team",
   "stats_filter": "[[\"Team\",\"enabled\",\"=\",1,false]]",
   "type": "DocType"
  }
 ],
 "title": "Team"
}
